baymesh/__init__.py
baymesh/baymesh_versions.py
baymesh/firmware_versions.py
baymesh/node_validation.py
baymesh/cli/__init__.py
baymesh/cli/__main__.py
baymesh/cli/devices.py
baymesh/cli/echo.py
baymesh/cli/node_setup.py
baymesh-0.7.2.dist-info/METADATA
baymesh-0.7.2.dist-info/WHEEL
baymesh-0.7.2.dist-info/entry_points.txt
baymesh-0.7.2.dist-info/licenses/LICENSE
baymesh-0.7.2.dist-info/RECORD
