Metadata-Version: 2.4
Name: baymesh
Version: 0.7.2
Summary: Baymesh command line and library for members of Bayme.sh
Project-URL: Repository, https://github.com/gtaylor/baymesh-cli
Maintainer: Greg Taylor
License-File: LICENSE
Classifier: Development Status :: 3 - Alpha
Classifier: License :: OSI Approved :: GNU General Public License v3 (GPLv3)
Classifier: Programming Language :: Python :: 3.11
Classifier: Programming Language :: Python :: 3.12
Classifier: Programming Language :: Python :: 3.13
Requires-Python: >=3.11
Requires-Dist: click>=8.1.8
Requires-Dist: meshtastic>=2.5.10
Requires-Dist: pyserial>=3.5
Requires-Dist: pyyaml>=6.0.2
Requires-Dist: requests>=2.32.3
